{
  "flora-dark":{
    "surface":          [31, 39, 27],
    "surface_sunken":   [53, 67, 46],
    "surface_raised":   [75, 95, 65],
    "text_body":        [212, 197, 160],
    "text_heading":     [226, 171, 111],
    "text_muted":       [124, 137, 116],
    "text_resting":     [172, 184, 164],
    "meta_indication":   [179, 212, 74],
    "meta_confirmation": [174, 115, 149],
    "chrome_sidebar":   [31, 39, 27],
    "chrome_panel":     [40, 52, 35],
    "chrome_toolbar":   [64, 82, 56],
    "border_card":      [46, 58, 39],
    "destructive":      [204, 82, 82]
  },

  "flora-light":{
    "surface":          [218, 228, 210],
    "surface_sunken":   [200, 212, 190],
    "surface_raised":   [184, 202, 170],
    "text_body":        [48, 62, 40],
    "text_heading":     [30, 72, 70],
    "text_muted":       [144, 158, 136],
    "text_resting":     [88, 104, 76],
    "meta_indication":  [100, 148, 28],
    "meta_confirmation":[148, 86, 120],
    "chrome_sidebar":   [218, 228, 210],
    "chrome_panel":     [208, 218, 200],
    "chrome_toolbar":   [228, 236, 222],
    "border_card":      [194, 206, 184],
    "destructive":      [204, 82, 82]
  },

  "paper-dark":{
    "surface":          [38, 30, 14],
    "surface_sunken":   [70, 54, 26],
    "surface_raised":   [90, 72, 34],
    "text_body":        [204, 188, 162],
    "text_heading":     [128, 178, 134],
    "text_muted":       [142, 126, 102],
    "text_resting":     [188, 172, 142],
    "meta_indication":  [196, 104, 38],
    "meta_confirmation":[84, 158, 92],
    "chrome_sidebar":   [38, 30, 14],
    "chrome_panel":     [50, 40, 20],
    "chrome_toolbar":   [82, 64, 32],
    "border_card":      [52, 42, 20],
    "destructive":      [204, 82, 82]
  },
  
  "paper-light":{
    "surface":          [242, 232, 210],
    "surface_sunken":   [226, 214, 190],
    "surface_raised":   [212, 200, 174],
    "text_body":        [70, 58, 42],
    "text_heading":     [88, 138, 90],
    "text_muted":       [168, 158, 136],
    "text_resting":     [112, 100, 80],
    "meta_indication":  [190, 88, 30],
    "meta_confirmation":[78, 138, 86],
    "chrome_sidebar":   [242, 232, 210],
    "chrome_panel":     [234, 222, 196],
    "chrome_toolbar":   [248, 240, 224],
    "border_card":      [218, 206, 182],
    "destructive":      [204, 82, 82]
  }
}
